pyreqver/__init__.py
pyreqver/main.py
pyreqver_cn-0.1.0.dist-info/licenses/LICENSE
pyreqver_cn-0.1.0.dist-info/METADATA
pyreqver_cn-0.1.0.dist-info/WHEEL
pyreqver_cn-0.1.0.dist-info/entry_points.txt
pyreqver_cn-0.1.0.dist-info/top_level.txt
pyreqver_cn-0.1.0.dist-info/RECORD
